koinput/__init__.py
koinput/inputs.py
koinput/menu.py
koinput/progress_bar.py
koinput-0.3.2.dist-info/WHEEL
koinput-0.3.2.dist-info/METADATA
koinput-0.3.2.dist-info/RECORD
