Metadata-Version: 2.1
Name: koinput
Version: 0.3.2
Summary: Maximal simplification of Input / Output for text programs.
Home-page: https://github.com/k0perX-X/koinput
Author: Николай Перминов
Author-email: kolya-perminov@ya.ru
Requires-Python: >=3.6,<4.0
Classifier: Programming Language :: Python :: 3
Classifier: Programming Language :: Python :: 3.6
Classifier: Programming Language :: Python :: 3.7
Classifier: Programming Language :: Python :: 3.8
Classifier: Programming Language :: Python :: 3.9
Requires-Dist: colorama (>=0.4.4,<0.5.0)
Project-URL: Repository, https://github.com/k0perX-X/koinput
